accnetbio
